db_navigator/__init__.py
db_navigator/databases.py
db_navigator/db_navigator.py
db_navigator/static/css/bootstrap.min.css
db_navigator/static/css/content.css
db_navigator/static/css/insert.css
db_navigator/static/css/login.css
db_navigator/static/css/main.css
db_navigator/static/css/fontawesome/css/all.min.css
db_navigator/static/css/fontawesome/webfonts/fa-regular-400.ttf
db_navigator/static/css/fontawesome/webfonts/fa-regular-400.woff2
db_navigator/static/css/fontawesome/webfonts/fa-solid-900.ttf
db_navigator/static/css/fontawesome/webfonts/fa-solid-900.woff2
db_navigator/static/html/base.html
db_navigator/static/html/index.html
db_navigator/static/html/login.html
db_navigator/static/html/sidebar.html
db_navigator/static/html/sql.html
db_navigator/static/html/table_base.html
db_navigator/static/html/table_content.html
db_navigator/static/html/table_insert.html
db_navigator/static/html/table_structure.html
db_navigator/static/img/icon.png
db_navigator/static/js/bootstrap.min.js
db_navigator/static/js/content.js
db_navigator/static/js/insert.js
db_navigator/static/js/sql.js
db_navigator/static/js/table.js
db_navigator/static/js/theme.js
DBNavigator-0.2.2.dist-info/METADATA
DBNavigator-0.2.2.dist-info/WHEEL
DBNavigator-0.2.2.dist-info/top_level.txt
DBNavigator-0.2.2.dist-info/RECORD
