Metadata-Version: 2.1
Name: DBNavigator
Version: 0.2.2
Summary: DataBase Navigator for Flask
Home-page: https://github.com/SuperZombi/DBNavigator
Author: Super_Zombi
Author-email: super.zombi.yt@gmail.com
Classifier: Programming Language :: Python :: 3
Classifier: License :: OSI Approved :: MIT License
Classifier: Operating System :: OS Independent
Requires-Python: >=3.6
Requires-Dist: Jinja2
Requires-Dist: Flask
